<annotation>
	<folder>dataset_cropped_300x300_2</folder>
	<filename>be4_78_yellow_violet_red_gold.jpg</filename>
	<path>C:\Users\kanji\Documents\myten\workspace\training_demo\images\dataset_cropped_300x300_2\be4_78_yellow_violet_red_gold.jpg</path>
	<source>
		<database>Unknown</database>
	</source>
	<size>
		<width>300</width>
		<height>300</height>
		<depth>3</depth>
	</size>
	<segmented>0</segmented>
	<object>
		<name>yellow_band</name>
		<pose>Unspecified</pose>
		<truncated>0</truncated>
		<difficult>0</difficult>
		<bndbox>
			<xmin>91</xmin>
			<ymin>110</ymin>
			<xmax>121</xmax>
			<ymax>173</ymax>
		</bndbox>
	</object>
	<object>
		<name>violet_band</name>
		<pose>Unspecified</pose>
		<truncated>0</truncated>
		<difficult>0</difficult>
		<bndbox>
			<xmin>126</xmin>
			<ymin>121</ymin>
			<xmax>152</xmax>
			<ymax>172</ymax>
		</bndbox>
	</object>
	<object>
		<name>red_band</name>
		<pose>Unspecified</pose>
		<truncated>0</truncated>
		<difficult>0</difficult>
		<bndbox>
			<xmin>159</xmin>
			<ymin>123</ymin>
			<xmax>187</xmax>
			<ymax>178</ymax>
		</bndbox>
	</object>
	<object>
		<name>gold_band</name>
		<pose>Unspecified</pose>
		<truncated>0</truncated>
		<difficult>0</difficult>
		<bndbox>
			<xmin>194</xmin>
			<ymin>124</ymin>
			<xmax>218</xmax>
			<ymax>186</ymax>
		</bndbox>
	</object>
</annotation>
